apipie/__init__.py
apipie/__main__.py
apipie/call.py
apipie/main.py
apipie/rate_limit.py
apipie-0.7.41.dist-info/METADATA
apipie-0.7.41.dist-info/WHEEL
apipie-0.7.41.dist-info/top_level.txt
apipie-0.7.41.dist-info/RECORD
