Metadata-Version: 2.4
Name: apipie
Version: 0.7.41
Summary: A short description of your package
Home-page: https://github.com/kokoslabs/apipie
Author: kokolabs
Author-email: tmpkokorocks@awsl.uk
Classifier: Programming Language :: Python :: 3
Classifier: License :: OSI Approved :: MIT License
Classifier: Operating System :: OS Independent
Requires-Python: >=3.7
Requires-Dist: sanic
Requires-Dist: requests
Dynamic: author
Dynamic: author-email
Dynamic: classifier
Dynamic: description
Dynamic: description-content-type
Dynamic: home-page
Dynamic: requires-dist
Dynamic: requires-python
Dynamic: summary
